streamsync_bubblemessage/__init__.py
streamsync_bubblemessage/extensions/style.css
streamsync_bubblemessage/extensions/templates.umd.js
streamsync_bubblemessage-0.0.2.dist-info/LICENSE
streamsync_bubblemessage-0.0.2.dist-info/METADATA
streamsync_bubblemessage-0.0.2.dist-info/WHEEL
streamsync_bubblemessage-0.0.2.dist-info/RECORD
