Metadata-Version: 2.1
Name: streamsync_bubblemessage
Version: 0.0.2
Summary: demo / template to distribute an extension for streamsync on pypi
Home-page: https://www.streamsync.cloud
License: MIT
Author: Fabien Arcellier
Author-email: fabien.arcellier@gmail.com
Requires-Python: >=3.9.2,<4.0.0
Classifier: Development Status :: 4 - Beta
Classifier: Environment :: Web Environment
Classifier: Intended Audience :: Developers
Classifier: License :: OSI Approved :: MIT License
Classifier: Operating System :: OS Independent
Classifier: Programming Language :: Python :: 3
Classifier: Programming Language :: Python :: 3.10
Classifier: Programming Language :: Python :: 3.11
Classifier: Topic :: Scientific/Engineering :: Visualization
Project-URL: Documentation, https://www.streamsync.cloud/custom-components.html
Project-URL: Repository, https://github.com/FabienArcellier/streamsync_bubblemessage
